doomsday/__init__.py
doomsday/cli.py
doomsday/methods.py
tests/__init__.py
tests/test_cli.py
tests/test_methods.py
doomsday-1.2.2.dist-info/LICENSE
doomsday-1.2.2.dist-info/METADATA
doomsday-1.2.2.dist-info/WHEEL
doomsday-1.2.2.dist-info/entry_points.txt
doomsday-1.2.2.dist-info/top_level.txt
doomsday-1.2.2.dist-info/RECORD
