Metadata-Version: 2.1
Name: doomsday
Version: 1.2.2
Summary: A command line Doomsday rule utility and trainer
Home-page: https://github.com/bradleypallen/doomsday
Author: Bradley P. Allen
License: MIT License
Platform: UNKNOWN
Classifier: Development Status :: 3 - Alpha
Classifier: Intended Audience :: End Users/Desktop
Classifier: License :: OSI Approved :: MIT License
Classifier: Operating System :: OS Independent
Classifier: Programming Language :: Python :: 3.6
Classifier: Programming Language :: Python :: 3.7
Classifier: Programming Language :: Python :: 3.8
Classifier: Programming Language :: Python :: 3.9
License-File: LICENSE
Requires-Dist: click (>=8.0.1)
Provides-Extra: test
Requires-Dist: pytest ; extra == 'test'
